conv_lstm/__init__.py
conv_lstm/conv_lstm.py
conv_lstm-0.1.2.dist-info/LICENSE
conv_lstm-0.1.2.dist-info/WHEEL
conv_lstm-0.1.2.dist-info/METADATA
conv_lstm-0.1.2.dist-info/RECORD
