Metadata-Version: 2.1
Name: conv-lstm
Version: 0.1.2
Summary: A PyTorch implementation for convolutional LSTM
Home-page: https://github.com/Jimexist/conv_lstm_pytorch
License: MIT
Author: Andrea Palazzi
Author-email: andrea.palazzi@unimore.it
Requires-Python: >=3.6
Classifier: License :: OSI Approved :: MIT License
Classifier: Programming Language :: Python :: 3
Classifier: Programming Language :: Python :: 3.6
Classifier: Programming Language :: Python :: 3.7
Classifier: Programming Language :: Python :: 3.8
Requires-Dist: torch (>=1.5.0)
Project-URL: Repository, https://github.com/Jimexist/conv_lstm_pytorch
